odoo/addons/sale_stock_last_date/README.rst
odoo/addons/sale_stock_last_date/__init__.py
odoo/addons/sale_stock_last_date/__manifest__.py
odoo/addons/sale_stock_last_date/hooks.py
odoo/addons/sale_stock_last_date/i18n/es.po
odoo/addons/sale_stock_last_date/i18n/sale_stock_last_date.pot
odoo/addons/sale_stock_last_date/models/__init__.py
odoo/addons/sale_stock_last_date/models/sale.py
odoo/addons/sale_stock_last_date/readme/CONTRIBUTORS.rst
odoo/addons/sale_stock_last_date/readme/DESCRIPTION.rst
odoo/addons/sale_stock_last_date/readme/USAGE.rst
odoo/addons/sale_stock_last_date/reports/__init__.py
odoo/addons/sale_stock_last_date/reports/sale_report.py
odoo/addons/sale_stock_last_date/reports/sale_report_view.xml
odoo/addons/sale_stock_last_date/static/description/icon.png
odoo/addons/sale_stock_last_date/static/description/index.html
odoo/addons/sale_stock_last_date/tests/__init__.py
odoo/addons/sale_stock_last_date/tests/test_sale_stock_last_date.py
odoo/addons/sale_stock_last_date/views/sale_order_view.xml
odoo12_addon_sale_stock_last_date-12.0.1.0.0.99.dev2.dist-info/METADATA
odoo12_addon_sale_stock_last_date-12.0.1.0.0.99.dev2.dist-info/WHEEL
odoo12_addon_sale_stock_last_date-12.0.1.0.0.99.dev2.dist-info/top_level.txt
odoo12_addon_sale_stock_last_date-12.0.1.0.0.99.dev2.dist-info/RECORD
